huaweicloudsdkantiddos/__init__.py
huaweicloudsdkantiddos/v1/__init__.py
huaweicloudsdkantiddos/v1/antiddos_async_client.py
huaweicloudsdkantiddos/v1/antiddos_client.py
huaweicloudsdkantiddos/v1/model/__init__.py
huaweicloudsdkantiddos/v1/model/create_default_config_request.py
huaweicloudsdkantiddos/v1/model/create_default_config_response.py
huaweicloudsdkantiddos/v1/model/d_dos_status.py
huaweicloudsdkantiddos/v1/model/daily_data.py
huaweicloudsdkantiddos/v1/model/daily_log.py
huaweicloudsdkantiddos/v1/model/ddos_config.py
huaweicloudsdkantiddos/v1/model/delete_default_config_request.py
huaweicloudsdkantiddos/v1/model/delete_default_config_response.py
huaweicloudsdkantiddos/v1/model/enable_defense_policy_request.py
huaweicloudsdkantiddos/v1/model/enable_defense_policy_response.py
huaweicloudsdkantiddos/v1/model/list_d_dos_status_request.py
huaweicloudsdkantiddos/v1/model/list_d_dos_status_response.py
huaweicloudsdkantiddos/v1/model/list_daily_log_request.py
huaweicloudsdkantiddos/v1/model/list_daily_log_response.py
huaweicloudsdkantiddos/v1/model/list_daily_report_request.py
huaweicloudsdkantiddos/v1/model/list_daily_report_response.py
huaweicloudsdkantiddos/v1/model/list_quota_request.py
huaweicloudsdkantiddos/v1/model/list_quota_response.py
huaweicloudsdkantiddos/v1/model/list_weekly_reports_request.py
huaweicloudsdkantiddos/v1/model/list_weekly_reports_response.py
huaweicloudsdkantiddos/v1/model/lts_config_request_and_response.py
huaweicloudsdkantiddos/v1/model/lts_config_request_and_response_lts_id_info.py
huaweicloudsdkantiddos/v1/model/open_anti_d_dos_service_request_body.py
huaweicloudsdkantiddos/v1/model/quota_response_ddos_quota.py
huaweicloudsdkantiddos/v1/model/show_d_dos_request.py
huaweicloudsdkantiddos/v1/model/show_d_dos_response.py
huaweicloudsdkantiddos/v1/model/show_d_dos_status_request.py
huaweicloudsdkantiddos/v1/model/show_d_dos_status_response.py
huaweicloudsdkantiddos/v1/model/show_default_config_request.py
huaweicloudsdkantiddos-3.1.184.dist-info/METADATA
huaweicloudsdkantiddos-3.1.184.dist-info/WHEEL
huaweicloudsdkantiddos-3.1.184.dist-info/licenses/LICENSE
huaweicloudsdkantiddos-3.1.184.dist-info/RECORD
